cuda/bench/__init__.py
cuda/bench/__init__.pyi
cuda/bench/py.typed
cuda/bench/cu12/_nvbench.cpython-310-x86_64-linux-gnu.so
cuda/bench/cu12/libnvbench.so
cuda/bench/cu13/_nvbench.cpython-310-x86_64-linux-gnu.so
cuda/bench/cu13/libnvbench.so
scripts/__init__.py
scripts/nvbench_compare.py
scripts/nvbench_histogram.py
scripts/nvbench_walltime.py
scripts/test_cmp.json
scripts/test_ref.json
scripts/nvbench_json/__init__.py
scripts/nvbench_json/reader.py
scripts/nvbench_json/version.py
cuda_bench-0.1.0.dist-info/METADATA
cuda_bench-0.1.0.dist-info/WHEEL
cuda_bench-0.1.0.dist-info/entry_points.txt
cuda_bench-0.1.0.dist-info/RECORD
