Metadata-Version: 2.1
Name: cuda-bench
Version: 0.1.0
Summary: CUDA Kernel Benchmarking Package
Author: NVIDIA Corporation
License: Apache-2.0 WITH LLVM-exception
Classifier: Development Status :: 4 - Beta
Classifier: Intended Audience :: Developers
Classifier: Topic :: Software Development :: Libraries :: Python Modules
Classifier: Programming Language :: Python :: 3 :: Only
Classifier: Programming Language :: Python :: 3.10
Classifier: Programming Language :: Python :: 3.11
Classifier: Programming Language :: Python :: 3.12
Classifier: Programming Language :: Python :: 3.13
Classifier: Environment :: GPU :: NVIDIA CUDA
Classifier: License :: OSI Approved :: Apache Software License
Classifier: Operating System :: POSIX :: Linux
Project-URL: Homepage, https://github.com/NVIDIA/nvbench
Project-URL: Repository, https://github.com/NVIDIA/nvbench
Project-URL: Issues, https://github.com/NVIDIA/nvbench/issues
Requires-Python: >=3.10
Requires-Dist: cuda-pathfinder
Provides-Extra: cu12
Requires-Dist: cuda-bindings<13.0.0,>=12.0.0; extra == "cu12"
Requires-Dist: nvidia-cuda-cupti-cu12; extra == "cu12"
Provides-Extra: cu13
Requires-Dist: cuda-bindings<14.0.0,>=13.0.0; extra == "cu13"
Requires-Dist: nvidia-cuda-cupti>=13.0; extra == "cu13"
Provides-Extra: test-cu12
Requires-Dist: cuda-bench[cu12]; extra == "test-cu12"
Requires-Dist: pytest; extra == "test-cu12"
Requires-Dist: cupy-cuda12x; extra == "test-cu12"
Requires-Dist: numba; extra == "test-cu12"
Provides-Extra: test-cu13
Requires-Dist: cuda-bench[cu13]; extra == "test-cu13"
Requires-Dist: pytest; extra == "test-cu13"
Requires-Dist: cupy-cuda13x; extra == "test-cu13"
Requires-Dist: numba; extra == "test-cu13"
Provides-Extra: test
Requires-Dist: pytest; extra == "test"
Requires-Dist: cupy-cuda12x; extra == "test"
Requires-Dist: numba; extra == "test"
Provides-Extra: tools
Requires-Dist: colorama; extra == "tools"
Requires-Dist: jsondiff; extra == "tools"
Requires-Dist: matplotlib; extra == "tools"
Requires-Dist: numpy; extra == "tools"
Requires-Dist: pandas; extra == "tools"
Requires-Dist: seaborn; extra == "tools"
Requires-Dist: tabulate; extra == "tools"
